PiLCDControl/LCD.py
PiLCDControl/_LCDControl.py
PiLCDControl/__init__.py
PiLCDControl-0.6.dist-info/METADATA
PiLCDControl-0.6.dist-info/WHEEL
PiLCDControl-0.6.dist-info/top_level.txt
PiLCDControl-0.6.dist-info/RECORD
